ChangeLog.rst
MANIFEST.in
README.rst
setup.cfg
setup.py
isotel/__init__.py
isotel/idm/__init__.py
isotel/idm/_urllib2.py
isotel/idm/_urllib3.py
isotel/idm/_version.py
isotel/idm/customstream.py
isotel/idm/ec.py
isotel/idm/gateway.py
isotel/idm/monodaq.py
isotel/idm/signal.py
isotel_idm.egg-info/PKG-INFO
isotel_idm.egg-info/SOURCES.txt
isotel_idm.egg-info/dependency_links.txt
isotel_idm.egg-info/requires.txt
isotel_idm.egg-info/top_level.txt