Metadata-Version: 1.1
Name: isotel-idm
Version: 1.0b21
Summary: A python framework for the ISOTEL Data-acquisition & Metering Smart Gateway for easy integration with Internet of Things.
Home-page: http://isotel.eu/idm
Author: Isotel Team
Author-email: pypi@isotel.eu
License: LGPL3.0
Keywords: idm gateway data acquisition metering server scalable sensor network protocols heterogeneous hardware devices DIY
Platform: UNKNOWN
Classifier: Development Status :: 4 - Beta
Classifier: Intended Audience :: Developers
Classifier: Intended Audience :: Education
Classifier: Intended Audience :: Science/Research
Classifier: Intended Audience :: Information Technology
Classifier: Intended Audience :: Telecommunications Industry
Classifier: Intended Audience :: Manufacturing
Classifier: Topic :: Communications
Classifier: Topic :: Home Automation
Classifier: Topic :: Software Development :: Embedded Systems
Classifier: Topic :: Scientific/Engineering :: Interface Engine/Protocol Translator
Classifier: Topic :: Terminals
Classifier: Topic :: Terminals :: Serial
Classifier: Framework :: Flask
Classifier: Framework :: IPython
Classifier: Framework :: Jupyter
Classifier: License :: OSI Approved :: GNU Lesser General Public License v3 (LGPLv3)
Classifier: Programming Language :: Python :: 3
Classifier: Programming Language :: Python :: 3.3
Classifier: Programming Language :: Python :: 3.4
Classifier: Programming Language :: Python :: 3.5
